TCLIService/TCLIService.py
TCLIService/__init__.py
TCLIService/constants.py
TCLIService/ttypes.py
pyquark/__init__.py
pyquark/common.py
pyquark/exc.py
pyquark/quark.py
pyquark/sasl_compat.py
pyquark/sqlalchemy_quark.py
quark_connector-0.7.1.dev0.dist-info/LICENSE
quark_connector-0.7.1.dev0.dist-info/METADATA
quark_connector-0.7.1.dev0.dist-info/WHEEL
quark_connector-0.7.1.dev0.dist-info/entry_points.txt
quark_connector-0.7.1.dev0.dist-info/top_level.txt
quark_connector-0.7.1.dev0.dist-info/RECORD
