Metadata-Version: 2.2
Name: quark-connector
Version: 0.7.1.dev0
Summary: Python interface to Quark
Author: transwarp
License: Apache License, Version 2.0
Classifier: Intended Audience :: Developers
Classifier: License :: OSI Approved :: Apache Software License
Classifier: Operating System :: OS Independent
Classifier: Topic :: Database :: Front-Ends
License-File: LICENSE
Requires-Dist: future
Requires-Dist: python-dateutil
Provides-Extra: quark
Requires-Dist: sasl>=0.2.1; extra == "quark"
Requires-Dist: thrift>=0.10.0; extra == "quark"
Requires-Dist: thrift_sasl>=0.1.0; extra == "quark"
Provides-Extra: quark-pure-sasl
Requires-Dist: pure-sasl>=0.6.2; extra == "quark-pure-sasl"
Requires-Dist: thrift>=0.10.0; extra == "quark-pure-sasl"
Requires-Dist: thrift_sasl>=0.1.0; extra == "quark-pure-sasl"
Provides-Extra: sqlalchemy
Requires-Dist: sqlalchemy>=1.3.0; extra == "sqlalchemy"
Provides-Extra: kerberos
Requires-Dist: requests_kerberos>=0.12.0; extra == "kerberos"
Dynamic: author
Dynamic: classifier
Dynamic: description
Dynamic: license
Dynamic: provides-extra
Dynamic: requires-dist
Dynamic: summary
